docs/conf.py
docs/contributing.rst
docs/index.rst
docs/installation.rst
lazy_text_classifiers/__init__.py
lazy_text_classifiers/constants.py
lazy_text_classifiers/logging_utils.py
lazy_text_classifiers/model_selection.py
lazy_text_classifiers/py.typed
lazy_text_classifiers/model_wrappers/__init__.py
lazy_text_classifiers/model_wrappers/estimator_base.py
lazy_text_classifiers/model_wrappers/fine_tuned_transformer.py
lazy_text_classifiers/model_wrappers/semantic_logit.py
lazy_text_classifiers/model_wrappers/setfit_transformer.py
lazy_text_classifiers/model_wrappers/tfidf_logit.py
lazy_text_classifiers/tests/conftest.py
lazy_text_classifiers/tests/test_empty.py
lazy_text_classifiers-0.1.0.dist-info/LICENSE
lazy_text_classifiers-0.1.0.dist-info/METADATA
lazy_text_classifiers-0.1.0.dist-info/WHEEL
lazy_text_classifiers-0.1.0.dist-info/top_level.txt
lazy_text_classifiers-0.1.0.dist-info/RECORD
