Metadata-Version: 2.1
Name: lazy-text-classifiers
Version: 0.1.0
Summary: Build and test a variety of text multi-class classification models.
Author-email: Eva Maxfield Brown <evamaxfieldbrown@gmail.com>
License: MIT License
Project-URL: Homepage, https://github.com/evamaxfield/lazy-text-classifiers
Project-URL: Bug Tracker, https://github.com/evamaxfield/lazy-text-classifiers/issues
Project-URL: Documentation, https://evamaxfield.github.io/lazy-text-classifiers
Project-URL: User Support, https://github.com/evamaxfield/lazy-text-classifiers/issues
Classifier: Development Status :: 4 - Beta
Classifier: Natural Language :: English
Classifier: Programming Language :: Python :: 3.8
Classifier: Programming Language :: Python :: 3.9
Classifier: Programming Language :: Python :: 3.10
Requires-Python: >=3.8
License-File: LICENSE
Requires-Dist: datasets (~=2.0)
Requires-Dist: embetter (~=0.3)
Requires-Dist: numpy
Requires-Dist: pandas (~=1.0)
Requires-Dist: scikit-learn (~=1.2)
Requires-Dist: sentence-transformers
Requires-Dist: setfit (~=0.5)
Requires-Dist: torch
Requires-Dist: transformers (~=4.0)
Provides-Extra: dev
Requires-Dist: ipython (>=8.4.0) ; extra == 'dev'
Provides-Extra: docs
Requires-Dist: m2r2 (>=0.2.7) ; extra == 'docs'
Requires-Dist: Sphinx (>=4.0.0) ; extra == 'docs'
Requires-Dist: furo (>=2022.4.7) ; extra == 'docs'
Requires-Dist: numpydoc ; extra == 'docs'
Requires-Dist: sphinx-copybutton ; extra == 'docs'
Requires-Dist: docutils (<0.19,>=0.18) ; extra == 'docs'
Provides-Extra: lint
Requires-Dist: black (>=22.3.0) ; extra == 'lint'
Requires-Dist: check-manifest (>=0.48) ; extra == 'lint'
Requires-Dist: ruff (>=0.0.216) ; extra == 'lint'
Requires-Dist: mypy (>=0.790) ; extra == 'lint'
Requires-Dist: pre-commit (>=2.20.0) ; extra == 'lint'
Provides-Extra: test
Requires-Dist: coverage (>=5.1) ; extra == 'test'
Requires-Dist: pytest (>=5.4.3) ; extra == 'test'
Requires-Dist: pytest-cov (>=2.9.0) ; extra == 'test'
Requires-Dist: pytest-raises (>=0.11) ; extra == 'test'
